coloria/__init__.py
coloria/_exceptions.py
coloria/_helpers.py
coloria/_rgb_gamut.py
coloria/_surface_gamut.py
coloria/_tools.py
coloria/_visible_gamut.py
coloria/colormaps.py
coloria/py.typed
coloria/cam/__init__.py
coloria/cam/_cam16.py
coloria/cam/_ciecam02.py
coloria/cam/_zcam.py
coloria/cat/__init__.py
coloria/cat/_bianco_schettini.py
coloria/cat/_bradford.py
coloria/cat/_cat02.py
coloria/cat/_cat16.py
coloria/cat/_cmccat2000.py
coloria/cat/_sharp.py
coloria/cat/_von_kries.py
coloria/cs/__init__.py
coloria/cs/_bracketing.py
coloria/cs/_cam02.py
coloria/cs/_cam16.py
coloria/cs/_cie1960ucs.py
coloria/cs/_ciehcl.py
coloria/cs/_cielab.py
coloria/cs/_cielch.py
coloria/cs/_cieluv.py
coloria/cs/_cieuvw.py
coloria/cs/_color_coordinates.py
coloria/cs/_color_space.py
coloria/cs/_din99.py
coloria/cs/_hct.py
coloria/cs/_hdr.py
coloria/cs/_helpers.py
coloria/cs/_hsl.py
coloria/cs/_hsv.py
coloria/cs/_hwb.py
coloria/cs/_ictcp.py
coloria/cs/_igpgtg.py
coloria/cs/_ipt.py
coloria/cs/_jzazbz.py
coloria/cs/_lch.py
coloria/cs/_oklab.py
coloria/cs/_osa_ucs.py
coloria/cs/_prolab.py
coloria/cs/_rlab.py
coloria/cs/_srgb.py
coloria/cs/_srlab2.py
coloria/cs/_xyy.py
coloria/cs/_xyz.py
coloria/data/__init__.py
coloria/data/color_distance.py
coloria/data/ellipse.py
coloria/data/helpers.py
coloria/data/hue_linearity.py
coloria/data/bfd_p/__init__.py
coloria/data/bfd_p/bfd-c.json
coloria/data/bfd_p/bfd-d65.json
coloria/data/bfd_p/bfd-m.json
coloria/data/combvd/__init__.py
coloria/data/ebner_fairchild/__init__.py
coloria/data/ebner_fairchild/ebner_fairchild.json
coloria/data/fairchild_chen/__init__.py
coloria/data/fairchild_chen/fairchild_chen.json
coloria/data/hung_berns/__init__.py
coloria/data/hung_berns/hb-table1.json
coloria/data/hung_berns/hb-table2.json
coloria/data/hung_berns/hb-table3.json
coloria/data/hung_berns/hb-table4.json
coloria/data/leeds/__init__.py
coloria/data/leeds/leeds.json
coloria/data/luo_rigg/__init__.py
coloria/data/luo_rigg/luo-rigg.json
coloria-0.14.5.dist-info/METADATA
coloria-0.14.5.dist-info/WHEEL
coloria-0.14.5.dist-info/top_level.txt
coloria-0.14.5.dist-info/RECORD
